bruhscript/__init__.py
bruhscript/core.py
bruhscript/plugins/__init__.py
bruhscript/plugins/file_plugin.py
bruhscript/plugins/math_plugin.py
BruhScript-1.0.3.dist-info/LICENSE
BruhScript-1.0.3.dist-info/METADATA
BruhScript-1.0.3.dist-info/WHEEL
BruhScript-1.0.3.dist-info/entry_points.txt
BruhScript-1.0.3.dist-info/top_level.txt
BruhScript-1.0.3.dist-info/RECORD
