Metadata-Version: 2.1
Name: BruhScript
Version: 1.0.3
Summary: A meme-based programming language that's surprisingly powerful.
Home-page: https://github.com/dimaniojk/BruhScript
Author: dimaniojk
Author-email: your.email@example.com
Classifier: Programming Language :: Python :: 3
Classifier: License :: OSI Approved :: MIT License
Classifier: Operating System :: OS Independent
Requires-Python: >=3.7
License-File: LICENSE
Requires-Dist: requests
